[
  {
    "time": null,
    "title": "房屋稅5月開徵 自住房屋須這日期前辦竣戶籍登記 非自住房屋出租能節稅",
    "url": "https://estate.ltn.com.tw/article/26824",
    "image": "https://img.ltn.com.tw/Upload/house/page/2026/01/29/260129-26824-1-8jEkH.jpg",
    "published_at": "2026-01-29T13:55:41+00:00",
    "source": "LTN"
  },
  {
    "time": "21:47",
    "title": "週五多雲到晴！白天高溫可達27度 入夜急降注意保暖",
    "url": "https://news.ltn.com.tw/news/life/breakingnews/5326685",
    "image": "https://img.ltn.com.tw/Upload/news/600/2026/01/29/php4ngIGZ.jpg",
    "published_at": "2026-01-29T13:55:41+00:00",
    "source": "LTN"
  },
  {
    "time": "21:47",
    "title": "盜版動漫畫、周邊讓日本年損破2兆 官方點名「這2國」最誇張",
    "url": "https://news.ltn.com.tw/news/world/breakingnews/5326638",
    "image": "https://img.ltn.com.tw/Upload/news/600/2026/01/29/phpJd8uka.jpg",
    "published_at": "2026-01-29T13:55:41+00:00",
    "source": "LTN"
  },
  {
    "time": "21:46",
    "title": "「消息不正確」 啦啦隊女孩遭點名闖SJ休息室 經紀公司發聲",
    "url": "https://ent.ltn.com.tw/news/breakingnews/5326734",
    "image": "https://img.ltn.com.tw/Upload/ent/page/800/2026/01/29/phpMR8OVZ.jpg",
    "published_at": "2026-01-29T13:55:41+00:00",
    "source": "LTN"
  },
  {
    "time": "21:46",
    "title": "日職》挑戰台灣神獸！徐若熙超狂目標 想打破郭泰源史上第一紀錄",
    "url": "https://sports.ltn.com.tw/news/breakingnews/5326716",
    "image": "https://img.ltn.com.tw/Upload/sports/page/800S/2026/01/29/phptfY6n7.jpg",
    "published_at": "2026-01-29T13:55:41+00:00",
    "source": "LTN"
  },
  {
    "time": "21:46",
    "title": "健康網》打呼變胖還恐猝死？ 醫：冬天睡眠缺氧「傷」心血管",
    "url": "https://health.ltn.com.tw/article/breakingnews/5325492",
    "image": "https://img.ltn.com.tw/Upload/health/page/800/2026/01/28/phpBAednO.jpg",
    "published_at": "2026-01-29T13:55:41+00:00",
    "source": "LTN"
  },
  {
    "time": "21:42",
    "title": "白蛇蹺家彰化溪湖出沒！「白化玉米蛇」1/30開放登記認養",
    "url": "https://news.ltn.com.tw/news/life/breakingnews/5326726",
    "image": "https://img.ltn.com.tw/Upload/news/600/2026/01/29/5326726_2_1.jpg",
    "published_at": "2026-01-29T13:55:41+00:00",
    "source": "LTN"
  },
  {
    "time": "21:41",
    "title": "「活人被寫死！」以國女子看新聞驚見自己慘死伊朗 拍片怒打臉",
    "url": "https://news.ltn.com.tw/news/world/breakingnews/5326575",
    "image": "https://img.ltn.com.tw/Upload/news/600/2026/01/29/phplTDRpD.jpg",
    "published_at": "2026-01-29T13:55:41+00:00",
    "source": "LTN"
  }
]