[
  {
    "time": "16:50",
    "title": "高市早苗啟程訪越澳 新版FOIP構想內容曝光",
    "url": "https://news.ltn.com.tw/news/world/breakingnews/5422325",
    "image": "https://img.ltn.com.tw/Upload/news/600/2026/05/01/phpiWYVcy.jpg",
    "published_at": "2026-05-01T08:55:29+00:00",
    "source": "LTN"
  },
  {
    "time": "16:48",
    "title": "苗栗公館鄉立游泳池完成整修 勞動節連假試營運免費進場",
    "url": "https://news.ltn.com.tw/news/life/breakingnews/5422300",
    "image": "https://img.ltn.com.tw/Upload/news/600/2026/05/01/5422300_2_1.jpg",
    "published_at": "2026-05-01T08:55:29+00:00",
    "source": "LTN"
  },
  {
    "time": "16:48",
    "title": "網球》九江男雙「台灣內戰」 許育修險勝莊吉生挺進4強",
    "url": "https://sports.ltn.com.tw/news/breakingnews/5422338",
    "image": "https://img.ltn.com.tw/Upload/sports/page/800S/2026/05/01/5422338_1.jpg",
    "published_at": "2026-05-01T08:55:29+00:00",
    "source": "LTN"
  },
  {
    "time": "16:48",
    "title": "鴨香飯闆娘忘鎖門遭小偷 警速逮慣竊找回贓款",
    "url": "https://news.ltn.com.tw/news/society/breakingnews/5422313",
    "image": "https://img.ltn.com.tw/Upload/news/600/2026/05/01/5422313_1_1.jpg",
    "published_at": "2026-05-01T08:55:29+00:00",
    "source": "LTN"
  },
  {
    "time": "16:47",
    "title": "阿伯噴檳榔汁、街友滿地「金流」 台東偏鄉客運司機開車做功德",
    "url": "https://news.ltn.com.tw/news/life/breakingnews/5422230",
    "image": "https://img.ltn.com.tw/Upload/news/600/2026/05/01/5422230_2_1.jpg",
    "published_at": "2026-05-01T08:55:29+00:00",
    "source": "LTN"
  },
  {
    "time": "16:46",
    "title": "先禮後兵！永和保福宮遶境 蘇巧慧、李四川同台握手、禮貌互動",
    "url": "https://news.ltn.com.tw/news/politics/breakingnews/5422316",
    "image": "https://img.ltn.com.tw/Upload/news/600/2026/05/01/5422316_1_1.jpg",
    "published_at": "2026-05-01T08:55:29+00:00",
    "source": "LTN"
  },
  {
    "time": "16:42",
    "title": "連續做愛8000天！AV男優清水健自爆GG變長了",
    "url": "https://ent.ltn.com.tw/news/breakingnews/5422311",
    "image": "https://img.ltn.com.tw/Upload/ent/page/800/2026/05/01/5422311_2.jpg",
    "published_at": "2026-05-01T08:55:29+00:00",
    "source": "LTN"
  },
  {
    "time": "16:42",
    "title": "板橋花市30週年結合母親節 打卡抽限定花花購物袋",
    "url": "https://news.ltn.com.tw/news/life/breakingnews/5422283",
    "image": "https://img.ltn.com.tw/Upload/news/600/2026/05/01/5422283_2_1.jpg",
    "published_at": "2026-05-01T08:55:29+00:00",
    "source": "LTN"
  }
]