[
  {
    "time": "01:21",
    "title": "美伊緊張升高 美軍將增派F-16和F-35赴中東",
    "url": "https://news.ltn.com.tw/news/world/breakingnews/5511871",
    "image": "https://news.ltn.com.tw/assets/images/all/250_ltn.png",
    "published_at": "2026-07-20T17:28:49+00:00",
    "source": "LTN"
  },
  {
    "time": "01:12",
    "title": "中東局勢緊張 歐洲股市收盤走勢分歧",
    "url": "https://ec.ltn.com.tw/article/breakingnews/5511869",
    "image": "https://ec.ltn.com.tw/assets/images/1200_ec.png",
    "published_at": "2026-07-20T17:28:49+00:00",
    "source": "LTN"
  },
  {
    "time": "00:44",
    "title": "被內鬼出賣！墨76歲大毒梟「五月」判終身監禁 終結40年毒品帝國",
    "url": "https://news.ltn.com.tw/news/world/breakingnews/5511863",
    "image": "https://img.ltn.com.tw/Upload/news/600/2026/07/21/5511863_1_1.jpg",
    "published_at": "2026-07-20T17:28:49+00:00",
    "source": "LTN"
  },
  {
    "time": "00:41",
    "title": "降低對美依賴！加拿大砸462億增購190輛裝甲車 另出資援烏35輛",
    "url": "https://news.ltn.com.tw/news/def/breakingnews/5511864",
    "image": "https://img.ltn.com.tw/Upload/def/page/800/2026/07/21/5511864_1_1.jpg",
    "published_at": "2026-07-20T17:28:49+00:00",
    "source": "LTN"
  },
  {
    "time": "00:31",
    "title": "7月下旬「3大重要星象」解密 國師唐綺陽：熬過「這階段」就是你的搶錢局！",
    "url": "https://ent.ltn.com.tw/news/breakingnews/5511845",
    "image": "https://img.ltn.com.tw/Upload/ent/page/800/2026/07/20/phpsY0aKF.jpg",
    "published_at": "2026-07-20T17:28:49+00:00",
    "source": "LTN"
  },
  {
    "time": "00:30",
    "title": "中國官媒AI影片辱菲律賓人是猴 菲媒貼「習維尼」圖嗆爆反擊！",
    "url": "https://news.ltn.com.tw/news/world/breakingnews/5511849",
    "image": "https://img.ltn.com.tw/Upload/news/600/2026/07/20/phpw0mLl5.png",
    "published_at": "2026-07-20T17:28:49+00:00",
    "source": "LTN"
  },
  {
    "time": "00:24",
    "title": "葡萄牙向義大利訂購3艘FREMM護衛艦",
    "url": "https://news.ltn.com.tw/news/def/breakingnews/5511798",
    "image": "https://img.ltn.com.tw/Upload/def/page/800/2026/07/21/phpOWrasz.jpg",
    "published_at": "2026-07-20T17:28:49+00:00",
    "source": "LTN"
  },
  {
    "time": "00:21",
    "title": "蔣萬安偕李四川探班 送換洗衣物挺絕食小雞",
    "url": "https://news.ltn.com.tw/news/politics/breakingnews/5511859",
    "image": "https://img.ltn.com.tw/Upload/news/600/2026/07/21/5511859_1_1.jpg",
    "published_at": "2026-07-20T17:28:49+00:00",
    "source": "LTN"
  }
]