[
  {
    "time": "06:16",
    "title": "得台灣者得天下？馬斯克談美中AI競賽 影片翻出掀台網熱議",
    "url": "https://news.ltn.com.tw/news/world/breakingnews/5453302",
    "image": "https://img.ltn.com.tw/Upload/news/600/2026/05/28/phpkYHIzD.png",
    "published_at": "2026-05-28T22:28:29+00:00",
    "source": "LTN"
  },
  {
    "time": "06:14",
    "title": "鋒面來襲！北東防短延時大雨 薔蜜颱風動向曝",
    "url": "https://news.ltn.com.tw/news/life/breakingnews/5453394",
    "image": "https://img.ltn.com.tw/Upload/news/600/2026/05/29/php9FljEj.jpg",
    "published_at": "2026-05-28T22:28:29+00:00",
    "source": "LTN"
  },
  {
    "time": "06:07",
    "title": "產品包裝有簡體字、脫口稱「大陸」惹議 雅方美女千金道歉了！",
    "url": "https://news.ltn.com.tw/news/politics/breakingnews/5453303",
    "image": "https://img.ltn.com.tw/Upload/news/600/2026/05/28/phpXUpaMR.png",
    "published_at": "2026-05-28T22:28:29+00:00",
    "source": "LTN"
  },
  {
    "time": "06:06",
    "title": "自曝曾怒掛馬大姊電話 金溥聰：馬英九對蕭旭岑二人不會「息事寧人」",
    "url": "https://news.ltn.com.tw/news/politics/breakingnews/5453304",
    "image": "https://img.ltn.com.tw/Upload/news/600/2026/05/28/php69rWMG.jpg",
    "published_at": "2026-05-28T22:28:29+00:00",
    "source": "LTN"
  },
  {
    "time": "06:04",
    "title": "把輝達進駐當政績 李四川「這件事」被網灌爆",
    "url": "https://news.ltn.com.tw/news/politics/breakingnews/5453262",
    "image": "https://img.ltn.com.tw/Upload/news/600/2026/05/28/phpsI9AyU.png",
    "published_at": "2026-05-28T22:28:29+00:00",
    "source": "LTN"
  },
  {
    "time": "06:03",
    "title": "北北基桃大雨特報！3縣市慎防大雷雨",
    "url": "https://news.ltn.com.tw/news/life/breakingnews/5453398",
    "image": "https://img.ltn.com.tw/Upload/news/600/2026/05/29/phpYKg3oX.png",
    "published_at": "2026-05-28T22:28:29+00:00",
    "source": "LTN"
  },
  {
    "time": "05:58",
    "title": "館長又去中國！參訪張雪機車猛舔刷愛國流量 遭創辦人當面打臉",
    "url": "https://news.ltn.com.tw/news/politics/breakingnews/5452863",
    "image": "https://img.ltn.com.tw/Upload/news/600/2026/05/28/phps9ewCa.png",
    "published_at": "2026-05-28T22:28:29+00:00",
    "source": "LTN"
  },
  {
    "time": "05:58",
    "title": "顛覆認知！實驗證實蚊子大腦受訓後 竟偏好叮咬噴灑防蚊液者",
    "url": "https://news.ltn.com.tw/news/world/breakingnews/5453356",
    "image": "https://img.ltn.com.tw/Upload/news/600/2026/05/28/5453356_1_1.jpg",
    "published_at": "2026-05-28T22:28:29+00:00",
    "source": "LTN"
  }
]