[
  {
    "time": "17:29",
    "title": "女足晉級世界盃抗中關鍵戰 駐澳處派員赴伯斯保公平",
    "url": "https://news.ltn.com.tw/news/life/breakingnews/5369336",
    "image": "https://img.ltn.com.tw/Upload/news/600/2026/03/13/phpQPE3Jr.jpg",
    "published_at": "2026-03-13T09:33:08+00:00",
    "source": "LTN"
  },
  {
    "time": "17:28",
    "title": "《逐玉》張凌赫、田曦薇十指緊扣 頭戴婚紗照曝光",
    "url": "https://ent.ltn.com.tw/news/breakingnews/5369325",
    "image": "https://img.ltn.com.tw/Upload/ent/page/800/2026/03/13/phpAI9gg6.jpg",
    "published_at": "2026-03-13T09:33:08+00:00",
    "source": "LTN"
  },
  {
    "time": "17:28",
    "title": "被陳智菡槓上！日議員上畠寛弘直接點名回擊：入境由日本決定",
    "url": "https://news.ltn.com.tw/news/politics/breakingnews/5369316",
    "image": "https://img.ltn.com.tw/Upload/news/600/2026/03/13/phpYEFJcn.jpg",
    "published_at": "2026-03-13T09:33:08+00:00",
    "source": "LTN"
  },
  {
    "time": "17:27",
    "title": "澎湖樂齡示範中心、樂齡學習數位示範體驗場域 教育部跨海視察",
    "url": "https://news.ltn.com.tw/news/life/breakingnews/5369367",
    "image": "https://img.ltn.com.tw/Upload/news/600/2026/03/13/5369367_1_1.jpg",
    "published_at": "2026-03-13T09:33:08+00:00",
    "source": "LTN"
  },
  {
    "time": "17:26",
    "title": "經典賽》難忘對台灣開轟東蛋變圖書館 巴札納談差點晉級：心情像坐雲霄飛車",
    "url": "https://sports.ltn.com.tw/news/breakingnews/5369311",
    "image": "https://img.ltn.com.tw/Upload/sports/page/800S/2026/03/13/phpskU4kP.jpg",
    "published_at": "2026-03-13T09:33:08+00:00",
    "source": "LTN"
  },
  {
    "time": "17:25",
    "title": "打到骨折！ 88折設定成88％OFF 港商GSE認賠：不開除員工",
    "url": "https://news.ltn.com.tw/news/world/breakingnews/5369292",
    "image": "https://img.ltn.com.tw/Upload/news/600/2026/03/13/phpG5RCZH.png",
    "published_at": "2026-03-13T09:33:08+00:00",
    "source": "LTN"
  },
  {
    "time": "17:24",
    "title": "美廉社母公司三商家購併購OK超商 公平會通過了",
    "url": "https://ec.ltn.com.tw/article/breakingnews/5369356",
    "image": "https://img.ltn.com.tw/Upload/business/page/800/2026/03/13/5369356_1.jpg",
    "published_at": "2026-03-13T09:33:08+00:00",
    "source": "LTN"
  },
  {
    "time": "17:24",
    "title": "假的啦！網傳卡達斷氣「台灣3/15大停電」 專家抓包：惡意訊息操作",
    "url": "https://news.ltn.com.tw/news/politics/breakingnews/5369355",
    "image": "https://img.ltn.com.tw/Upload/news/600/2026/03/13/5369355_1_1.jpg",
    "published_at": "2026-03-13T09:33:08+00:00",
    "source": "LTN"
  }
]