[
  {
    "time": "00:40",
    "title": "日網大讚高市早苗金句：不敢挑戰的國家不會有未來！",
    "url": "https://news.ltn.com.tw/news/world/breakingnews/5315371",
    "image": "https://img.ltn.com.tw/Upload/news/600/2026/01/19/phpaGk1Aa.png",
    "published_at": "2026-01-19T17:19:08+00:00",
    "source": "LTN"
  },
  {
    "time": "00:33",
    "title": "嚇爆！馬年沖犯流年煞 「散霉運」扭轉氣場3指南",
    "url": "https://ent.ltn.com.tw/news/breakingnews/5315375",
    "image": "https://img.ltn.com.tw/Upload/ent/page/800/2026/01/19/phpOBqkPf.jpg",
    "published_at": "2026-01-19T17:19:08+00:00",
    "source": "LTN"
  },
  {
    "time": "00:28",
    "title": "黃國昌帶出國防機密被抓包 他「日行一善」：翻成英文寄給美國務院！",
    "url": "https://news.ltn.com.tw/news/politics/breakingnews/5315370",
    "image": "https://img.ltn.com.tw/Upload/news/600/2026/01/19/phpxNg8GZ.png",
    "published_at": "2026-01-19T17:19:08+00:00",
    "source": "LTN"
  },
  {
    "time": "00:23",
    "title": "台鐵高雄車站2025日運量增5.6％ 為4特等站唯一正成長",
    "url": "https://news.ltn.com.tw/news/life/breakingnews/5315378",
    "image": "https://img.ltn.com.tw/Upload/news/600/2026/01/20/5315378_1_1.jpg",
    "published_at": "2026-01-19T17:19:08+00:00",
    "source": "LTN"
  },
  {
    "time": "00:20",
    "title": "高雄春節4天停收垃圾 除夕夜不收垃圾",
    "url": "https://news.ltn.com.tw/news/life/breakingnews/5315376",
    "image": "https://img.ltn.com.tw/Upload/news/600/2026/01/19/5315376_1_1.jpg",
    "published_at": "2026-01-19T17:19:08+00:00",
    "source": "LTN"
  },
  {
    "time": "00:16",
    "title": "被打入冷宮！中共黨媒重提「地攤經濟」 認能助內需起死回生",
    "url": "https://ec.ltn.com.tw/article/breakingnews/5315383",
    "image": "https://img.ltn.com.tw/Upload/business/page/800/2026/01/20/5315383_1_1.jpg",
    "published_at": "2026-01-19T17:19:08+00:00",
    "source": "LTN"
  },
  {
    "time": "00:11",
    "title": "高捷與北港朝天宮聯手 貓站長蜜柑「虎袍」加身",
    "url": "https://news.ltn.com.tw/news/life/breakingnews/5315377",
    "image": "https://img.ltn.com.tw/Upload/news/600/2026/01/20/5315377_1_1.jpg",
    "published_at": "2026-01-19T17:19:08+00:00",
    "source": "LTN"
  },
  {
    "time": "00:05",
    "title": "陳玉珍發文重申「我不是台灣人」 他PO一張「抹茶豆腐冰」KO！",
    "url": "https://news.ltn.com.tw/news/politics/breakingnews/5315281",
    "image": "https://img.ltn.com.tw/Upload/news/600/2026/01/19/php1EjAc8.png",
    "published_at": "2026-01-19T17:19:08+00:00",
    "source": "LTN"
  }
]