[
  {
    "time": "09:19",
    "title": "蘋果預告 50 週年活動！3 大重磅產品成焦點、iPhone 迎史上最大變動",
    "url": "https://3c.ltn.com.tw/news/65276",
    "image": "https://img.ltn.com.tw/Upload/3c/page/2026/03/13/260313-65276-1.jpeg",
    "published_at": "2026-03-13T01:26:02+00:00",
    "source": "LTN"
  },
  {
    "time": "09:16",
    "title": "亞洲最大木雕濟公活佛換新衣 「百倍大神袍」純手工打造金龍浮雕",
    "url": "https://news.ltn.com.tw/news/life/breakingnews/5368716",
    "image": "https://img.ltn.com.tw/Upload/news/600/2026/03/13/5368716_1_1.jpg",
    "published_at": "2026-03-13T01:26:02+00:00",
    "source": "LTN"
  },
  {
    "time": "09:15",
    "title": "油價狂飆 川普要求聯準會立即降息",
    "url": "https://ec.ltn.com.tw/article/breakingnews/5368671",
    "image": "https://img.ltn.com.tw/Upload/business/page/800/2026/03/13/phpHnhz05.jpg",
    "published_at": "2026-03-13T01:26:02+00:00",
    "source": "LTN"
  },
  {
    "time": "09:14",
    "title": "雙拳不敵四掌 馬公男孤身前往談判遭2兄弟砍殺",
    "url": "https://news.ltn.com.tw/news/society/breakingnews/5368720",
    "image": "https://img.ltn.com.tw/Upload/news/600/2026/03/13/5368720_1_1.jpg",
    "published_at": "2026-03-13T01:26:02+00:00",
    "source": "LTN"
  },
  {
    "time": "09:14",
    "title": "好險！彰化驚傳民宅神明廳火警 還好只燒到一點點",
    "url": "https://news.ltn.com.tw/news/society/breakingnews/5368717",
    "image": "https://img.ltn.com.tw/Upload/news/600/2026/03/13/5368717_1_1.jpg",
    "published_at": "2026-03-13T01:26:02+00:00",
    "source": "LTN"
  },
  {
    "time": "09:13",
    "title": "全球能源危機來了？國際油價又暴漲",
    "url": "https://ec.ltn.com.tw/article/breakingnews/5368724",
    "image": "https://img.ltn.com.tw/Upload/business/page/800/2026/03/13/phpjDir30.jpg",
    "published_at": "2026-03-13T01:26:02+00:00",
    "source": "LTN"
  },
  {
    "time": "09:10",
    "title": "Lexus 新年式 LM 配備升級登場！新增 LED 迎賓光毯營造尊榮體驗",
    "url": "https://auto.ltn.com.tw/news/31153",
    "image": "https://img.ltn.com.tw/Upload/auto/page/2026/03/12/260312-31153-10-i1f81.jpg",
    "published_at": "2026-03-13T01:26:02+00:00",
    "source": "LTN"
  },
  {
    "time": "09:10",
    "title": "張凌赫「最強哄妻術」曝光 合體田曦薇重現《逐玉》陳皮糖吻",
    "url": "https://ent.ltn.com.tw/news/breakingnews/5368609",
    "image": "https://img.ltn.com.tw/Upload/ent/page/800/2026/03/13/5368609_2.jpg",
    "published_at": "2026-03-13T01:26:02+00:00",
    "source": "LTN"
  }
]