[
  {
    "time": "05:30",
    "title": "兒少權法大修 擬設工作證制度／條文由118增為165 草案預告30天、下月中辦公聽會",
    "url": "https://news.ltn.com.tw/news/life/paper/1751882",
    "image": "https://img.ltn.com.tw/Upload/news/600/2026/04/22/64.jpg",
    "published_at": "2026-04-21T21:38:41+00:00",
    "source": "LTN"
  },
  {
    "time": "05:30",
    "title": "模擬馬太鞍溪堰塞湖 縮比實驗 揭潰決之謎",
    "url": "https://news.ltn.com.tw/news/life/paper/1751857",
    "image": "https://img.ltn.com.tw/Upload/news/600/2026/04/22/40.jpg",
    "published_at": "2026-04-21T21:38:41+00:00",
    "source": "LTN"
  },
  {
    "time": "05:30",
    "title": "日本鬆綁武器出口 可售17國",
    "url": "https://news.ltn.com.tw/news/world/paper/1751933",
    "image": "https://img.ltn.com.tw/Upload/news/600/2026/04/22/118.jpg",
    "published_at": "2026-04-21T21:38:41+00:00",
    "source": "LTN"
  },
  {
    "time": "05:30",
    "title": "日自衛隊戰車砲彈膛炸 3死1重傷",
    "url": "https://news.ltn.com.tw/news/world/paper/1751934",
    "image": "https://img.ltn.com.tw/Upload/news/600/2026/04/22/119.jpg",
    "published_at": "2026-04-21T21:38:41+00:00",
    "source": "LTN"
  },
  {
    "time": "05:30",
    "title": "大聯盟首安、首打點出爐 李灝宇開心：終於做到了",
    "url": "https://sports.ltn.com.tw/news/paper/1751862",
    "image": "https://img.ltn.com.tw/Upload/sports/page/800S/2026/04/22/45.jpg",
    "published_at": "2026-04-21T21:38:41+00:00",
    "source": "LTN"
  },
  {
    "time": "05:30",
    "title": "教部發5.4萬張終身學習券 最高抵免1500元",
    "url": "https://news.ltn.com.tw/news/life/paper/1751856",
    "image": "https://img.ltn.com.tw/Upload/news/600/2026/04/22/39.jpg",
    "published_at": "2026-04-21T21:38:41+00:00",
    "source": "LTN"
  },
  {
    "time": "05:30",
    "title": "蕭旭岑：國民黨有人長期A錢 自清稱「不能因此以為我也會做一樣的事」",
    "url": "https://news.ltn.com.tw/news/politics/paper/1751860",
    "image": "https://img.ltn.com.tw/Upload/news/600/2026/04/22/43.jpg",
    "published_at": "2026-04-21T21:38:41+00:00",
    "source": "LTN"
  },
  {
    "time": "05:30",
    "title": "鄭習會作戲？》府譴責：中國善意是假 威脅是真",
    "url": "https://news.ltn.com.tw/news/politics/paper/1751838",
    "image": "https://img.ltn.com.tw/Upload/news/600/2026/04/22/19.jpg",
    "published_at": "2026-04-21T21:38:41+00:00",
    "source": "LTN"
  }
]