[
  {
    "time": "14:22",
    "title": "女星「為愛頂罪」吃牢飯20年 出獄遭渣尪背叛淚簽離婚書",
    "url": "https://ent.ltn.com.tw/news/breakingnews/5322422",
    "image": "https://img.ltn.com.tw/Upload/ent/page/800/2026/01/26/5322422_1.jpg",
    "published_at": "2026-01-26T06:28:47+00:00",
    "source": "LTN"
  },
  {
    "time": "14:21",
    "title": "馬年添財氣 銀行致贈發財小物力助客戶「財運暢旺」",
    "url": "https://ec.ltn.com.tw/article/breakingnews/5322423",
    "image": "https://img.ltn.com.tw/Upload/business/page/800/2026/01/26/5322423_2.jpg",
    "published_at": "2026-01-26T06:28:47+00:00",
    "source": "LTN"
  },
  {
    "time": "14:20",
    "title": "獨家》第6屆EPPD登場 將討論落實台美AI供應鏈合作",
    "url": "https://ec.ltn.com.tw/article/breakingnews/5322424",
    "image": "https://img.ltn.com.tw/Upload/business/page/800/2026/01/26/5322424_1.jpg",
    "published_at": "2026-01-26T06:28:47+00:00",
    "source": "LTN"
  },
  {
    "time": "14:19",
    "title": "BLACKPINK演唱會 張曼玉潮人打扮低調朝聖",
    "url": "https://ent.ltn.com.tw/news/breakingnews/5322413",
    "image": "https://img.ltn.com.tw/Upload/ent/page/800/2026/01/26/phpAh6Hro.jpg",
    "published_at": "2026-01-26T06:28:47+00:00",
    "source": "LTN"
  },
  {
    "time": "14:18",
    "title": "不是特斯拉！車主最愛5款電動車揭曉 第1名竟是「它」",
    "url": "https://ec.ltn.com.tw/article/breakingnews/5322236",
    "image": "https://img.ltn.com.tw/Upload/business/page/800/2026/01/26/phpuJxPR7.jpg",
    "published_at": "2026-01-26T06:28:47+00:00",
    "source": "LTN"
  },
  {
    "time": "14:17",
    "title": "台股站上三萬二 0056順利填息",
    "url": "https://ec.ltn.com.tw/article/breakingnews/5322408",
    "image": "https://img.ltn.com.tw/Upload/business/page/800/2026/01/26/5322408_1.jpg",
    "published_at": "2026-01-26T06:28:47+00:00",
    "source": "LTN"
  },
  {
    "time": "14:17",
    "title": "立榮班機傳機械異常停飛 緊急簽轉他航輸運旅客",
    "url": "https://news.ltn.com.tw/news/life/breakingnews/5322411",
    "image": "https://img.ltn.com.tw/Upload/news/600/2026/01/26/5322411_1_1.jpg",
    "published_at": "2026-01-26T06:28:47+00:00",
    "source": "LTN"
  },
  {
    "time": "14:16",
    "title": "TPBL》新北國王補強洋將 「籃球詩人」喬丹重返台灣",
    "url": "https://sports.ltn.com.tw/news/breakingnews/5322415",
    "image": "https://img.ltn.com.tw/Upload/sports/page/800S/2026/01/26/5322415_1.jpg",
    "published_at": "2026-01-26T06:28:47+00:00",
    "source": "LTN"
  }
]