[
  {
    "time": "15:28",
    "title": "嘉縣前議員黃芳蘭母子涉詐助理費 二審維持無罪",
    "url": "https://news.ltn.com.tw/news/society/breakingnews/5327312",
    "image": "https://img.ltn.com.tw/Upload/news/600/2026/01/30/5327312_1_1.jpg",
    "published_at": "2026-01-30T07:36:03+00:00",
    "source": "LTN"
  },
  {
    "time": "15:26",
    "title": "取代促進生產抗生素 嘉大、畜試所研發「發酵副產物飼料」",
    "url": "https://news.ltn.com.tw/news/life/breakingnews/5327320",
    "image": "https://img.ltn.com.tw/Upload/news/600/2026/01/30/5327320_1_1.jpg",
    "published_at": "2026-01-30T07:36:03+00:00",
    "source": "LTN"
  },
  {
    "time": "15:25",
    "title": "加油族注意！下週油價估最多漲0.4元 柴油恐漲0.6元",
    "url": "https://ec.ltn.com.tw/article/breakingnews/5327348",
    "image": "https://img.ltn.com.tw/Upload/business/page/800/2026/01/30/5327348_1.jpg",
    "published_at": "2026-01-30T07:36:03+00:00",
    "source": "LTN"
  },
  {
    "time": "15:25",
    "title": "洩稅務資料損商譽 川普告美國稅局索賠100億美元",
    "url": "https://news.ltn.com.tw/news/world/breakingnews/5327303",
    "image": "https://img.ltn.com.tw/Upload/news/600/2026/01/30/phpHu7atF.jpg",
    "published_at": "2026-01-30T07:36:03+00:00",
    "source": "LTN"
  },
  {
    "time": "15:24",
    "title": "國1寶山段大貨車撞路肩小貨車 司機臟器外露當場死亡",
    "url": "https://news.ltn.com.tw/news/society/breakingnews/5327341",
    "image": "https://img.ltn.com.tw/Upload/news/600/2026/01/30/5327341_1_1.jpg",
    "published_at": "2026-01-30T07:36:03+00:00",
    "source": "LTN"
  },
  {
    "time": "15:23",
    "title": "賣到缺貨！東南亞唯一黃金銷量下滑的國家是「它」",
    "url": "https://ec.ltn.com.tw/article/breakingnews/5327287",
    "image": "https://img.ltn.com.tw/Upload/business/page/800/2026/01/30/phpdmDpLV.jpg",
    "published_at": "2026-01-30T07:36:03+00:00",
    "source": "LTN"
  },
  {
    "time": "15:23",
    "title": "台南北區歲末送暖 近35萬元善款物資嘉惠逾百長者、弱勢戶",
    "url": "https://news.ltn.com.tw/news/life/breakingnews/5327262",
    "image": "https://img.ltn.com.tw/Upload/news/600/2026/01/30/5327262_1_1.jpg",
    "published_at": "2026-01-30T07:36:03+00:00",
    "source": "LTN"
  },
  {
    "time": "15:21",
    "title": "健康網》冬天關節卡卡鬧脾氣 醫列4大隱形殺手害退化",
    "url": "https://health.ltn.com.tw/article/breakingnews/5323832",
    "image": "https://img.ltn.com.tw/Upload/health/page/800/2026/01/27/phpsPyxIH.jpg",
    "published_at": "2026-01-30T07:36:03+00:00",
    "source": "LTN"
  }
]