[
  {
    "time": "23:25",
    "title": "無關艾普斯坦！前駐美大使「中國因素」國安審查未過 英相陷危機",
    "url": "https://news.ltn.com.tw/news/world/breakingnews/5409215",
    "image": "https://img.ltn.com.tw/Upload/news/600/2026/04/19/phpJgJRxv.jpg",
    "published_at": "2026-04-19T15:32:00+00:00",
    "source": "LTN"
  },
  {
    "time": "23:21",
    "title": "健康網》被叮後腫好幾天 醫說明如何分辨「蜂窩性組織炎」",
    "url": "https://health.ltn.com.tw/article/breakingnews/5404981",
    "image": "https://img.ltn.com.tw/Upload/health/page/800/2026/04/15/phpcpAeH5.jpg",
    "published_at": "2026-04-19T15:32:00+00:00",
    "source": "LTN"
  },
  {
    "time": "23:16",
    "title": "",
    "url": "https://news.ltn.com.tw/news/art/breakingnews/5409222",
    "image": "https://img.ltn.com.tw/Upload/art/page/800/2026/04/19/5409222_2.jpg",
    "published_at": "2026-04-19T15:32:00+00:00",
    "source": "LTN"
  },
  {
    "time": "23:14",
    "title": "",
    "url": "https://news.ltn.com.tw/news/art/breakingnews/5409213",
    "image": "https://img.ltn.com.tw/Upload/art/page/800/2026/04/19/5409213_1.jpg",
    "published_at": "2026-04-19T15:32:00+00:00",
    "source": "LTN"
  },
  {
    "time": "23:13",
    "title": "還想當立委！李貞秀聲請「假處分」文件 嗆：是我的搶不走",
    "url": "https://news.ltn.com.tw/news/politics/breakingnews/5409219",
    "image": "https://img.ltn.com.tw/Upload/news/600/2026/04/19/5409219_1_1.jpg",
    "published_at": "2026-04-19T15:32:00+00:00",
    "source": "LTN"
  },
  {
    "time": "23:06",
    "title": "UBA》宋昕澔宣布不參加台灣職籃選秀 旅外考慮這3國",
    "url": "https://sports.ltn.com.tw/news/breakingnews/5409218",
    "image": "https://img.ltn.com.tw/Upload/sports/page/800S/2026/04/19/php8l0mXi.jpg",
    "published_at": "2026-04-19T15:32:00+00:00",
    "source": "LTN"
  },
  {
    "time": "23:04",
    "title": "UBA冠軍賽》真的是我嗎？政大大三隊長徐得祈驚喜拿FMVP",
    "url": "https://sports.ltn.com.tw/news/breakingnews/5409216",
    "image": "https://img.ltn.com.tw/Upload/sports/page/800S/2026/04/19/phpM05Sbs.jpg",
    "published_at": "2026-04-19T15:32:00+00:00",
    "source": "LTN"
  },
  {
    "time": "23:04",
    "title": "保加利亞5年內第8次國會選舉登場 親俄前總統聲勢領先",
    "url": "https://news.ltn.com.tw/news/world/breakingnews/5409118",
    "image": "https://img.ltn.com.tw/Upload/news/600/2026/04/19/php4273V2.jpg",
    "published_at": "2026-04-19T15:32:00+00:00",
    "source": "LTN"
  }
]