[
  {
    "time": "14:30",
    "title": "別對iPhone 18 Pro期望太高！專家：只是iPhone 17 Pro「s版」",
    "url": "https://3c.ltn.com.tw/news/64956",
    "image": "https://img.ltn.com.tw/Upload/3c/page/2026/02/11/260211-64956-1.jpeg",
    "published_at": "2026-02-21T06:34:02+00:00",
    "source": "LTN"
  },
  {
    "time": "14:30",
    "title": "定點臨托+1！ 北市婦女培力中心設點 年中推新版預約系統",
    "url": "https://news.ltn.com.tw/news/life/breakingnews/5347261",
    "image": "https://img.ltn.com.tw/Upload/news/600/2026/02/21/5347261_1_1.jpg",
    "published_at": "2026-02-21T06:34:02+00:00",
    "source": "LTN"
  },
  {
    "time": "14:26",
    "title": "石碇五路財神廟走春人車潮湧現 新店警加強宣導與疏導",
    "url": "https://news.ltn.com.tw/news/society/breakingnews/5347257",
    "image": "https://img.ltn.com.tw/Upload/news/600/2026/02/21/5347257_1_1.jpg",
    "published_at": "2026-02-21T06:34:02+00:00",
    "source": "LTN"
  },
  {
    "time": "14:24",
    "title": "拒收地瓜乾！ 高市早苗揭官邸生活辛酸 誠實發言驚動幕僚中斷拍攝",
    "url": "https://news.ltn.com.tw/news/world/breakingnews/5347207",
    "image": "https://img.ltn.com.tw/Upload/news/600/2026/02/21/php0Fj1Yx.jpg",
    "published_at": "2026-02-21T06:34:02+00:00",
    "source": "LTN"
  },
  {
    "time": "14:23",
    "title": "大年初五北市傳槍響 醫美診所董事長腿部中彈",
    "url": "https://news.ltn.com.tw/news/society/breakingnews/5347255",
    "image": "https://img.ltn.com.tw/Upload/news/600/2026/02/21/5347255_2_1.jpg",
    "published_at": "2026-02-21T06:34:02+00:00",
    "source": "LTN"
  },
  {
    "time": "14:22",
    "title": "鴻海合資印度半導體封測廠 總理莫迪今參加動土典禮",
    "url": "https://ec.ltn.com.tw/article/breakingnews/5347253",
    "image": "https://img.ltn.com.tw/Upload/business/page/800/2026/02/21/5347253_1.jpg",
    "published_at": "2026-02-21T06:34:02+00:00",
    "source": "LTN"
  },
  {
    "time": "14:21",
    "title": "NBA》米契爾生涯第100次單場30分 感謝球迷：我要再拿100個！",
    "url": "https://sports.ltn.com.tw/news/breakingnews/5347216",
    "image": "https://img.ltn.com.tw/Upload/sports/page/800S/2026/02/21/php7vgvyS.jpg",
    "published_at": "2026-02-21T06:34:02+00:00",
    "source": "LTN"
  },
  {
    "time": "14:20",
    "title": "離婚後首度曬年夜飯！ 陳妍希素顏入鏡驚艷網友",
    "url": "https://ent.ltn.com.tw/news/breakingnews/5347242",
    "image": "https://img.ltn.com.tw/Upload/ent/page/800/2026/02/21/phpmeyQ7f.jpg",
    "published_at": "2026-02-21T06:34:02+00:00",
    "source": "LTN"
  }
]