[
  {
    "time": "14:40",
    "title": "Toyota 高層人事異動 原財務長近健太升任新社長",
    "url": "https://auto.ltn.com.tw/news/30852",
    "image": "https://img.ltn.com.tw/Upload/auto/page/2026/02/06/260206-30852-10-CVwJF.jpg",
    "published_at": "2026-02-06T06:44:45+00:00",
    "source": "LTN"
  },
  {
    "time": "14:38",
    "title": "力拚過半！ 王定宇、黃婕陪同台南3人登記議員初選",
    "url": "https://news.ltn.com.tw/news/politics/breakingnews/5334888",
    "image": "https://img.ltn.com.tw/Upload/news/600/2026/02/06/5334888_1_1.jpg",
    "published_at": "2026-02-06T06:44:45+00:00",
    "source": "LTN"
  },
  {
    "time": "14:38",
    "title": "黃金大跌後還能買嗎？華爾街老將一句話潑冷水",
    "url": "https://ec.ltn.com.tw/article/breakingnews/5334636",
    "image": "https://img.ltn.com.tw/Upload/business/page/800/2026/02/06/phpOu77eq.jpg",
    "published_at": "2026-02-06T06:44:45+00:00",
    "source": "LTN"
  },
  {
    "time": "14:37",
    "title": "在大聯盟沒錢怎麼活？郭泓志淚揭「記憶中的味道」",
    "url": "https://ent.ltn.com.tw/news/breakingnews/5334902",
    "image": "https://img.ltn.com.tw/Upload/ent/page/800/2026/02/06/5334902_4.jpg",
    "published_at": "2026-02-06T06:44:45+00:00",
    "source": "LTN"
  },
  {
    "time": "14:35",
    "title": "《豆腐媽媽》武行演員高樓墜落 未婚妻現身痛訴：急診吐了4大袋血",
    "url": "https://ent.ltn.com.tw/news/breakingnews/5334908",
    "image": "https://img.ltn.com.tw/Upload/ent/page/800/2026/02/06/5334908_1.jpg",
    "published_at": "2026-02-06T06:44:45+00:00",
    "source": "LTN"
  },
  {
    "time": "14:35",
    "title": "屏東市歸園第三納骨塔上樑 今年完工啟用",
    "url": "https://news.ltn.com.tw/news/life/breakingnews/5334847",
    "image": "https://img.ltn.com.tw/Upload/news/600/2026/02/06/5334847_1_1.jpg",
    "published_at": "2026-02-06T06:44:45+00:00",
    "source": "LTN"
  },
  {
    "time": "14:34",
    "title": "PLG》「馬爾他巨獸」德古拉加入洋基本週有望亮相 錢韋成評價柯瓦隆表現",
    "url": "https://sports.ltn.com.tw/news/breakingnews/5334919",
    "image": "https://img.ltn.com.tw/Upload/sports/page/800S/2026/02/06/5334919_1.jpg",
    "published_at": "2026-02-06T06:44:45+00:00",
    "source": "LTN"
  },
  {
    "time": "14:33",
    "title": "夢境成真！夢見跌入聚寶盆 花蓮婦人隔天刮中100萬",
    "url": "https://ec.ltn.com.tw/article/breakingnews/5334918",
    "image": "https://img.ltn.com.tw/Upload/business/page/800/2026/02/06/5334918_1.jpg",
    "published_at": "2026-02-06T06:44:45+00:00",
    "source": "LTN"
  }
]