[
  {
    "time": "02:19",
    "title": "全球原油動脈告急！阿曼海域油輪遇襲4傷 伊朗禁航荷姆茲海峽",
    "url": "https://news.ltn.com.tw/news/world/breakingnews/5355449",
    "image": "https://img.ltn.com.tw/Upload/news/600/2026/03/02/phphwtTZz.jpg",
    "published_at": "2026-03-01T18:24:44+00:00",
    "source": "LTN"
  },
  {
    "time": "02:06",
    "title": "川普：美軍擊斃48位伊朗領導人 會與德黑蘭對話",
    "url": "https://news.ltn.com.tw/news/world/breakingnews/5355448",
    "image": "https://news.ltn.com.tw/assets/images/all/250_ltn.png",
    "published_at": "2026-03-01T18:24:44+00:00",
    "source": "LTN"
  },
  {
    "time": "01:24",
    "title": "川普稱伊朗求和已同意對話 嘆高層死傷殆盡早該讓步",
    "url": "https://news.ltn.com.tw/news/world/breakingnews/5355444",
    "image": "https://img.ltn.com.tw/Upload/news/600/2026/03/02/5355444_1_1.jpg",
    "published_at": "2026-03-01T18:24:44+00:00",
    "source": "LTN"
  },
  {
    "time": "01:23",
    "title": "美以聯手空襲 伊朗前總統艾馬丹加傳死訊",
    "url": "https://news.ltn.com.tw/news/world/breakingnews/5355429",
    "image": "https://img.ltn.com.tw/Upload/news/600/2026/03/01/phpv1pzKk.jpg",
    "published_at": "2026-03-01T18:24:44+00:00",
    "source": "LTN"
  },
  {
    "time": "01:21",
    "title": "戰爭部證實：史詩怒火行動已致美軍3死5重傷",
    "url": "https://news.ltn.com.tw/news/world/breakingnews/5355445",
    "image": "https://news.ltn.com.tw/assets/images/all/250_ltn.png",
    "published_at": "2026-03-01T18:24:44+00:00",
    "source": "LTN"
  },
  {
    "time": "01:16",
    "title": "斬首哈米尼難撼動政權 革命衛隊實力猶存 恐走向軍事獨裁",
    "url": "https://news.ltn.com.tw/news/world/breakingnews/5355442",
    "image": "https://img.ltn.com.tw/Upload/news/600/2026/03/02/5355442_1_1.jpg",
    "published_at": "2026-03-01T18:24:44+00:00",
    "source": "LTN"
  },
  {
    "time": "00:46",
    "title": "美軍擒委斬伊朗！展現1超強實力 許美華：台灣再看不懂真的瞎了眼",
    "url": "https://news.ltn.com.tw/news/politics/breakingnews/5355423",
    "image": "https://img.ltn.com.tw/Upload/news/600/2026/03/01/phpefUwwY.png",
    "published_at": "2026-03-01T18:24:44+00:00",
    "source": "LTN"
  },
  {
    "time": "00:39",
    "title": "英防相：伊朗報復行為日益無差別 有指管失控隱憂",
    "url": "https://news.ltn.com.tw/news/world/breakingnews/5355441",
    "image": "https://news.ltn.com.tw/assets/images/all/250_ltn.png",
    "published_at": "2026-03-01T18:24:44+00:00",
    "source": "LTN"
  }
]