[
  {
    "time": "10:42",
    "title": "Toyota 皇冠家族日本出清中！Crown Crossover、Sport 今年秋季迎升級",
    "url": "https://auto.ltn.com.tw/news/31999",
    "image": "https://img.ltn.com.tw/Upload/auto/page/2026/06/10/260610-31999-43-MiGGy.jpg",
    "published_at": "2026-06-10T02:46:20+00:00",
    "source": "LTN"
  },
  {
    "time": "10:40",
    "title": "陸委會禁地方首長參加海峽論壇 國台辦跳腳嗆「假民主真獨裁」",
    "url": "https://news.ltn.com.tw/news/politics/breakingnews/5467019",
    "image": "https://img.ltn.com.tw/Upload/news/600/2026/06/10/5467019_1_1.jpg",
    "published_at": "2026-06-10T02:46:20+00:00",
    "source": "LTN"
  },
  {
    "time": "10:40",
    "title": "毒駕恍惚撞車還想溜 搜出「喪屍煙彈」收押",
    "url": "https://news.ltn.com.tw/news/society/breakingnews/5467013",
    "image": "https://img.ltn.com.tw/Upload/news/600/2026/06/10/5467013_2_1.jpg",
    "published_at": "2026-06-10T02:46:20+00:00",
    "source": "LTN"
  },
  {
    "time": "10:39",
    "title": "馬文君又出手 砍陸軍特戰傘訓預算2億元",
    "url": "https://news.ltn.com.tw/news/politics/breakingnews/5466993",
    "image": "https://img.ltn.com.tw/Upload/news/600/2026/06/10/5466993_1_1.jpg",
    "published_at": "2026-06-10T02:46:20+00:00",
    "source": "LTN"
  },
  {
    "time": "10:38",
    "title": "李四川「三重」台語發音惹議 侯友宜：2種說法都聽過",
    "url": "https://news.ltn.com.tw/news/politics/breakingnews/5467012",
    "image": "https://img.ltn.com.tw/Upload/news/600/2026/06/10/5467012_1_1.jpg",
    "published_at": "2026-06-10T02:46:20+00:00",
    "source": "LTN"
  },
  {
    "time": "10:37",
    "title": "核三廠又遭影射雨後造「黃泥」 廠方澄清：各地野溪地表逕流",
    "url": "https://news.ltn.com.tw/news/life/breakingnews/5466989",
    "image": "https://img.ltn.com.tw/Upload/news/600/2026/06/10/5466989_1_1.jpg",
    "published_at": "2026-06-10T02:46:20+00:00",
    "source": "LTN"
  },
  {
    "time": "10:36",
    "title": "殷瑋強勢回應何孟樺「人民是我老闆」 蔣萬安：人民本來就是我們的老闆",
    "url": "https://news.ltn.com.tw/news/politics/breakingnews/5466990",
    "image": "https://img.ltn.com.tw/Upload/news/600/2026/06/10/5466990_1_1.jpg",
    "published_at": "2026-06-10T02:46:20+00:00",
    "source": "LTN"
  },
  {
    "time": "10:35",
    "title": "手搖飲當水喝 結石引發腎水腫 廚師「痛到腿軟」",
    "url": "https://health.ltn.com.tw/article/breakingnews/5466986",
    "image": "https://img.ltn.com.tw/Upload/health/page/800/2026/06/10/5466986_1.jpg",
    "published_at": "2026-06-10T02:46:20+00:00",
    "source": "LTN"
  }
]