[
  {
    "time": "01:03",
    "title": "收割？法戴高樂號航艦打擊群赴紅海 聯手英護航荷姆茲海峽",
    "url": "https://news.ltn.com.tw/news/world/breakingnews/5428239",
    "image": "https://img.ltn.com.tw/Upload/news/600/2026/05/07/5428239_1_1.jpg",
    "published_at": "2026-05-06T17:25:10+00:00",
    "source": "LTN"
  },
  {
    "time": "01:01",
    "title": "女山友獨攻雪山斷聯多日 親友PO尋人啟事 跑山獸與雪羊籲協尋",
    "url": "https://news.ltn.com.tw/news/life/breakingnews/5428232",
    "image": "https://img.ltn.com.tw/Upload/news/600/2026/05/07/phptfZ6k5.jpg",
    "published_at": "2026-05-06T17:25:10+00:00",
    "source": "LTN"
  },
  {
    "time": "00:52",
    "title": "民眾黨能用錢「買」不分區立委？ 林靖冠全說了 驚人金額曝光",
    "url": "https://news.ltn.com.tw/news/politics/breakingnews/5428105",
    "image": "https://img.ltn.com.tw/Upload/news/600/2026/05/06/phpu3VfSj.jpg",
    "published_at": "2026-05-06T17:25:10+00:00",
    "source": "LTN"
  },
  {
    "time": "00:49",
    "title": "愛爾麗爆針孔偷拍！常如山、特助聲押 女總經理500萬交保",
    "url": "https://news.ltn.com.tw/news/society/breakingnews/5428233",
    "image": "https://img.ltn.com.tw/Upload/news/600/2026/05/07/5428233_1_1.jpg",
    "published_at": "2026-05-06T17:25:10+00:00",
    "source": "LTN"
  },
  {
    "time": "00:48",
    "title": "台南芭樂倫敦參展後團購熱銷 逾400顆空運抵英國",
    "url": "https://ec.ltn.com.tw/article/breakingnews/5428238",
    "image": "https://ec.ltn.com.tw/assets/images/1200_ec.png",
    "published_at": "2026-05-06T17:25:10+00:00",
    "source": "LTN"
  },
  {
    "time": "00:44",
    "title": "台北暗夜槍響！轎車撞傷路撿警 遭警開7槍逃逸",
    "url": "https://news.ltn.com.tw/news/society/breakingnews/5428227",
    "image": "https://img.ltn.com.tw/Upload/news/600/2026/05/07/phpsk3643.jpg",
    "published_at": "2026-05-06T17:25:10+00:00",
    "source": "LTN"
  },
  {
    "time": "00:30",
    "title": "中東和平露曙光 歐股收漲油價回落",
    "url": "https://ec.ltn.com.tw/article/breakingnews/5428228",
    "image": "https://ec.ltn.com.tw/assets/images/1200_ec.png",
    "published_at": "2026-05-06T17:25:10+00:00",
    "source": "LTN"
  },
  {
    "time": "00:26",
    "title": "瓦解詐騙洗錢鏈》空殼貿易公司「順發成功」涉洗錢10億 8人聲押",
    "url": "https://news.ltn.com.tw/news/society/breakingnews/5428225",
    "image": "https://img.ltn.com.tw/Upload/news/600/2026/05/07/5428225_1_1.jpg",
    "published_at": "2026-05-06T17:25:10+00:00",
    "source": "LTN"
  }
]