[
  {
    "time": "00:48",
    "title": "桃園淹大水！他騎車下秒疑跌水溝「咕嚕咕嚕」 驚險第一視角曝光",
    "url": "https://news.ltn.com.tw/news/life/breakingnews/5505359",
    "image": "https://img.ltn.com.tw/Upload/news/600/2026/07/14/phpCSjvKT.jpg",
    "published_at": "2026-07-14T17:06:15+00:00",
    "source": "LTN"
  },
  {
    "time": "00:36",
    "title": "FCCC最新報告：外媒報導涉台新聞 在中國遭遇的打壓越來越大！",
    "url": "https://news.ltn.com.tw/news/politics/breakingnews/5505457",
    "image": "https://img.ltn.com.tw/Upload/news/600/2026/07/14/php9fXFmN.png",
    "published_at": "2026-07-14T17:06:15+00:00",
    "source": "LTN"
  },
  {
    "time": "00:31",
    "title": "大暑迎三合火局！柯柏成：3生肖乘勢而上「4招開運」大旺15天",
    "url": "https://ent.ltn.com.tw/news/breakingnews/5505462",
    "image": "https://img.ltn.com.tw/Upload/ent/page/800/2026/07/14/phpIVODJB.jpg",
    "published_at": "2026-07-14T17:06:15+00:00",
    "source": "LTN"
  },
  {
    "time": "00:20",
    "title": "撞2學童致重傷 萬榮鄉公所約僱人員竟拒絕酒測",
    "url": "https://news.ltn.com.tw/news/society/breakingnews/5505463",
    "image": "https://img.ltn.com.tw/Upload/news/600/2026/07/14/5505463_1_1.jpg",
    "published_at": "2026-07-14T17:06:15+00:00",
    "source": "LTN"
  },
  {
    "time": "00:12",
    "title": "女童逛一中街遭強迫推銷、押訂金 家長已向警方報案",
    "url": "https://news.ltn.com.tw/news/society/breakingnews/5505464",
    "image": "https://img.ltn.com.tw/Upload/news/600/2026/07/14/5505464_1_1.jpg",
    "published_at": "2026-07-14T17:06:15+00:00",
    "source": "LTN"
  },
  {
    "time": "23:59",
    "title": "幼貓遭丟出車外險墜河 獲救萌樣曝光",
    "url": "https://news.ltn.com.tw/news/world/breakingnews/5504972",
    "image": "https://img.ltn.com.tw/Upload/news/600/2026/07/14/phpOeLIg4.jpg",
    "published_at": "2026-07-14T17:06:15+00:00",
    "source": "LTN"
  },
  {
    "time": "23:55",
    "title": "批卓榮泰是「三沒院長」 國民黨：致癌油沒真相、沒道歉、沒下台",
    "url": "https://news.ltn.com.tw/news/politics/breakingnews/5505459",
    "image": "https://img.ltn.com.tw/Upload/news/600/2026/07/14/5505459_1_1.jpg",
    "published_at": "2026-07-14T17:06:15+00:00",
    "source": "LTN"
  },
  {
    "time": "23:52",
    "title": "與波灣國家達成投資協議！川普取消荷姆茲通行費 持續封鎖伊朗",
    "url": "https://news.ltn.com.tw/news/world/breakingnews/5505460",
    "image": "https://img.ltn.com.tw/Upload/news/600/2026/07/14/5505460_1_1.jpg",
    "published_at": "2026-07-14T17:06:15+00:00",
    "source": "LTN"
  }
]