[
  {
    "time": "05:12",
    "title": "NBA總冠軍G3溫班亞馬推頭惹議 川普力挺尼克批裁判",
    "url": "https://sports.ltn.com.tw/news/breakingnews/5468137",
    "image": "https://sports.ltn.com.tw/assets/images/rwd/1200_sport.png",
    "published_at": "2026-06-10T21:23:03+00:00",
    "source": "LTN"
  },
  {
    "time": "04:12",
    "title": "川普說會去看世足賽 FIFA：總統將頒獎給冠軍隊",
    "url": "https://sports.ltn.com.tw/news/breakingnews/5468134",
    "image": "https://sports.ltn.com.tw/assets/images/rwd/1200_sport.png",
    "published_at": "2026-06-10T21:23:03+00:00",
    "source": "LTN"
  },
  {
    "time": "04:12",
    "title": "川普揚言再次打擊伊朗 國際油價上揚",
    "url": "https://ec.ltn.com.tw/article/breakingnews/5468133",
    "image": "https://ec.ltn.com.tw/assets/images/1200_ec.png",
    "published_at": "2026-06-10T21:23:03+00:00",
    "source": "LTN"
  },
  {
    "time": "03:54",
    "title": "詹姆斯時代雜誌專訪 自認是史上最偉大球員",
    "url": "https://sports.ltn.com.tw/news/breakingnews/5468131",
    "image": "https://sports.ltn.com.tw/assets/images/rwd/1200_sport.png",
    "published_at": "2026-06-10T21:23:03+00:00",
    "source": "LTN"
  },
  {
    "time": "03:00",
    "title": "《TAIPEI TIMES》 Taiwan posts second-lowest monthly births in May",
    "url": "https://news.ltn.com.tw/news/focus/breakingnews/5468071",
    "image": "https://img.ltn.com.tw/Upload/news/600/2026/06/10/phpYRIA36.jpg",
    "published_at": "2026-06-10T21:23:03+00:00",
    "source": "LTN"
  },
  {
    "time": "03:00",
    "title": "《TAIPEI TIMES》 ‘Gray zone’ tactics used as substitute to war: think tank",
    "url": "https://news.ltn.com.tw/news/focus/breakingnews/5468068",
    "image": "https://img.ltn.com.tw/Upload/news/600/2026/06/10/phpoSOhw6.jpg",
    "published_at": "2026-06-10T21:23:03+00:00",
    "source": "LTN"
  },
  {
    "time": "03:00",
    "title": "《TAIPEI TIMES》 HIMARS fired off west coast in live-fire drill",
    "url": "https://news.ltn.com.tw/news/focus/breakingnews/5468069",
    "image": "https://img.ltn.com.tw/Upload/news/600/2026/06/10/php2dHyuk.jpg",
    "published_at": "2026-06-10T21:23:03+00:00",
    "source": "LTN"
  },
  {
    "time": "03:00",
    "title": "《TAIPEI TIMES》 Greenpeace warns about overfishing",
    "url": "https://news.ltn.com.tw/news/focus/breakingnews/5468070",
    "image": "https://img.ltn.com.tw/Upload/news/600/2026/06/10/phprkcTT6.jpg",
    "published_at": "2026-06-10T21:23:03+00:00",
    "source": "LTN"
  }
]