[
  {
    "time": "01:37",
    "title": "板橋大觀路家庭宮廟火警 疑神桌電線走火 夫妻嗆傷送醫",
    "url": "https://news.ltn.com.tw/news/society/breakingnews/5411609",
    "image": "https://img.ltn.com.tw/Upload/news/600/2026/04/22/phpfYIWnI.jpg",
    "published_at": "2026-04-21T17:55:27+00:00",
    "source": "LTN"
  },
  {
    "time": "00:54",
    "title": "台鐵深夜事故！男闖湖口站軌道遭撞亡 雙向列車大延誤",
    "url": "https://news.ltn.com.tw/news/society/breakingnews/5411605",
    "image": "https://img.ltn.com.tw/Upload/news/600/2026/04/22/phprndwmb.jpg",
    "published_at": "2026-04-21T17:55:27+00:00",
    "source": "LTN"
  },
  {
    "time": "00:48",
    "title": "美伊新和談前景不明 歐股收盤挫跌",
    "url": "https://ec.ltn.com.tw/article/breakingnews/5411606",
    "image": "https://ec.ltn.com.tw/assets/images/1200_ec.png",
    "published_at": "2026-04-21T17:55:27+00:00",
    "source": "LTN"
  },
  {
    "time": "00:48",
    "title": "新竹湖口車站列車事故 鐵警調查原因",
    "url": "https://news.ltn.com.tw/news/society/breakingnews/5411607",
    "image": "https://news.ltn.com.tw/assets/images/all/250_ltn.png",
    "published_at": "2026-04-21T17:55:27+00:00",
    "source": "LTN"
  },
  {
    "time": "00:33",
    "title": "中國阻撓賴清德出訪友邦 綠委曝2重點：惠台措施是毒藥裹糖衣！",
    "url": "https://news.ltn.com.tw/news/politics/breakingnews/5411587",
    "image": "https://img.ltn.com.tw/Upload/news/600/2026/04/21/phpiUHQdY.png",
    "published_at": "2026-04-21T17:55:27+00:00",
    "source": "LTN"
  },
  {
    "time": "00:30",
    "title": "金居爆違約交割1.1億元 今年以來最大筆",
    "url": "https://ec.ltn.com.tw/article/breakingnews/5411604",
    "image": "https://ec.ltn.com.tw/assets/images/1200_ec.png",
    "published_at": "2026-04-21T17:55:27+00:00",
    "source": "LTN"
  },
  {
    "time": "00:30",
    "title": "未來30天星象大震盪！12星座「繫好安全帶」先避坑、再衝刺",
    "url": "https://ent.ltn.com.tw/news/breakingnews/5411562",
    "image": "https://img.ltn.com.tw/Upload/ent/page/800/2026/04/21/php8Pcaw3.jpg",
    "published_at": "2026-04-21T17:55:27+00:00",
    "source": "LTN"
  },
  {
    "time": "00:27",
    "title": "藤井風10/31世巡首場到高雄 陳其邁：期待這次驚喜",
    "url": "https://news.ltn.com.tw/news/life/breakingnews/5411602",
    "image": "https://img.ltn.com.tw/Upload/news/600/2026/04/22/5411602_1_1.jpg",
    "published_at": "2026-04-21T17:55:27+00:00",
    "source": "LTN"
  }
]