[
  {
    "time": "12:30",
    "title": "Roots聯名LOOPY萌翻登場！Gen Z最愛迷因萌寵韓國小海狸爆紅",
    "url": "https://istyle.ltn.com.tw/article/39546",
    "image": "https://img.ltn.com.tw/Upload/style/page/2026/04/01/o-260401-39546-1-lpGKh.jpg",
    "published_at": "2026-04-05T04:33:12+00:00",
    "source": "LTN"
  },
  {
    "time": "12:27",
    "title": "不要命！鐵道花旗木大爆發 遊客闖鐵道拍照年年上演",
    "url": "https://news.ltn.com.tw/news/life/breakingnews/5393814",
    "image": "https://img.ltn.com.tw/Upload/news/600/2026/04/05/5393814_2_1.jpg",
    "published_at": "2026-04-05T04:33:12+00:00",
    "source": "LTN"
  },
  {
    "time": "12:24",
    "title": "台南永康蜈蜞潭中排魚群暴斃 採檢調查水質",
    "url": "https://news.ltn.com.tw/news/life/breakingnews/5393831",
    "image": "https://img.ltn.com.tw/Upload/news/600/2026/04/05/5393831_1_1.jpg",
    "published_at": "2026-04-05T04:33:12+00:00",
    "source": "LTN"
  },
  {
    "time": "12:22",
    "title": "健康網》恙蟲≠蟲！ 醫破解90％人都搞錯了",
    "url": "https://health.ltn.com.tw/article/breakingnews/5393516",
    "image": "https://img.ltn.com.tw/Upload/health/page/800/2026/04/04/php8722rX.jpg",
    "published_at": "2026-04-05T04:33:12+00:00",
    "source": "LTN"
  },
  {
    "time": "12:21",
    "title": "新基金募集潮湧現！投信搶推多檔ETF新品",
    "url": "https://ec.ltn.com.tw/article/breakingnews/5393829",
    "image": "https://img.ltn.com.tw/Upload/business/page/800/2026/04/05/5393829_1.jpg",
    "published_at": "2026-04-05T04:33:12+00:00",
    "source": "LTN"
  },
  {
    "time": "12:20",
    "title": "三菱越野神主牌 Pajero 最快 8 月全球首發！正面對決 Toyota Land Cruiser",
    "url": "https://auto.ltn.com.tw/news/31384",
    "image": "https://img.ltn.com.tw/Upload/auto/page/2026/04/04/260404-31384-48-v7Crq.png",
    "published_at": "2026-04-05T04:33:12+00:00",
    "source": "LTN"
  },
  {
    "time": "12:12",
    "title": "金塊擊退馬刺收下8連勝 今日NBA戰績",
    "url": "https://sports.ltn.com.tw/news/breakingnews/5393822",
    "image": "https://img.ltn.com.tw/Upload/sports/page/800S/2026/04/05/phpn7qVWS.jpg",
    "published_at": "2026-04-05T04:33:12+00:00",
    "source": "LTN"
  },
  {
    "time": "12:11",
    "title": "空軍總司令部舊址小辭典",
    "url": "https://news.ltn.com.tw/news/politics/breakingnews/5393787",
    "image": "https://img.ltn.com.tw/Upload/news/600/2026/04/05/5393787_1_1.jpg",
    "published_at": "2026-04-05T04:33:12+00:00",
    "source": "LTN"
  }
]