[
  {
    "time": "03:00",
    "title": "上萬輛偉士牌羅馬車聚 慶祝經典車款問世80年",
    "url": "https://news.ltn.com.tw/news/world/breakingnews/5487198",
    "image": "https://news.ltn.com.tw/assets/images/all/250_ltn.png",
    "published_at": "2026-06-28T19:08:11+00:00",
    "source": "LTN"
  },
  {
    "time": "03:00",
    "title": "《TAIPEI TIMES》 Mandopop celebrated at 37th Golden Melody Awards",
    "url": "https://news.ltn.com.tw/news/focus/breakingnews/5487146",
    "image": "https://img.ltn.com.tw/Upload/news/600/2026/06/28/phpY53kMI.jpg",
    "published_at": "2026-06-28T19:08:11+00:00",
    "source": "LTN"
  },
  {
    "time": "03:00",
    "title": "《TAIPEI TIMES》 Older single households hit new high",
    "url": "https://news.ltn.com.tw/news/focus/breakingnews/5487145",
    "image": "https://img.ltn.com.tw/Upload/news/600/2026/06/28/phpoeI52n.jpg",
    "published_at": "2026-06-28T19:08:11+00:00",
    "source": "LTN"
  },
  {
    "time": "03:00",
    "title": "《TAIPEI TIMES》 Defense net may be finished this year",
    "url": "https://news.ltn.com.tw/news/focus/breakingnews/5487138",
    "image": "https://img.ltn.com.tw/Upload/news/600/2026/06/28/phpyfrvMd.jpg",
    "published_at": "2026-06-28T19:08:11+00:00",
    "source": "LTN"
  },
  {
    "time": "03:00",
    "title": "《TAIPEI TIMES》 China using ‘free trip’ as united front tactic: source",
    "url": "https://news.ltn.com.tw/news/focus/breakingnews/5487143",
    "image": "https://img.ltn.com.tw/Upload/news/600/2026/06/28/php0PTJRx.jpg",
    "published_at": "2026-06-28T19:08:11+00:00",
    "source": "LTN"
  },
  {
    "time": "03:00",
    "title": "《TAIPEI TIMES》 Yuanta upgrades Taiwan’s GDP growth to 11.05％",
    "url": "https://news.ltn.com.tw/news/focus/breakingnews/5487139",
    "image": "https://img.ltn.com.tw/Upload/news/600/2026/06/28/phpLJItN9.jpg",
    "published_at": "2026-06-28T19:08:11+00:00",
    "source": "LTN"
  },
  {
    "time": "03:00",
    "title": "《TAIPEI TIMES》 Police arrest 63 following etomidate drug reclassification",
    "url": "https://news.ltn.com.tw/news/focus/breakingnews/5487144",
    "image": "https://img.ltn.com.tw/Upload/news/600/2026/06/28/phpc84MuA.jpg",
    "published_at": "2026-06-28T19:08:11+00:00",
    "source": "LTN"
  },
  {
    "time": "03:00",
    "title": "《TAIPEI TIMES》 China ethnicity law restricts room for neutrality: official",
    "url": "https://news.ltn.com.tw/news/focus/breakingnews/5487140",
    "image": "https://img.ltn.com.tw/Upload/news/600/2026/06/28/phpM9tAcj.jpg",
    "published_at": "2026-06-28T19:08:11+00:00",
    "source": "LTN"
  }
]