[
  {
    "time": "15:57",
    "title": "響應川普！ 歐盟考慮派遣海軍協助荷姆茲海峽通行",
    "url": "https://news.ltn.com.tw/news/world/breakingnews/5371998",
    "image": "https://img.ltn.com.tw/Upload/news/600/2026/03/16/phpEhtNW2.jpg",
    "published_at": "2026-03-16T08:04:26+00:00",
    "source": "LTN"
  },
  {
    "time": "15:56",
    "title": "73萬存股族遭棄養！投信2月下旬一路大買這檔金融 一出手就苦吞第1",
    "url": "https://ec.ltn.com.tw/article/breakingnews/5372030",
    "image": "https://img.ltn.com.tw/Upload/business/page/800/2026/03/16/phpImPzBx.jpg",
    "published_at": "2026-03-16T08:04:26+00:00",
    "source": "LTN"
  },
  {
    "time": "15:56",
    "title": "屏東家扶逆轉人生 2位受助兒長大成社工陪伴弱勢青年",
    "url": "https://news.ltn.com.tw/news/life/breakingnews/5372002",
    "image": "https://img.ltn.com.tw/Upload/news/600/2026/03/16/5372002_1.jpg",
    "published_at": "2026-03-16T08:04:26+00:00",
    "source": "LTN"
  },
  {
    "time": "15:56",
    "title": "連續58天單日冠軍！《陽光女子合唱團》成影史前十唯一國片",
    "url": "https://ent.ltn.com.tw/news/breakingnews/5372000",
    "image": "https://img.ltn.com.tw/Upload/ent/page/800/2026/03/16/phpSUJchX.jpg",
    "published_at": "2026-03-16T08:04:26+00:00",
    "source": "LTN"
  },
  {
    "time": "15:56",
    "title": "亞矽創3年前打掉重練卻空轉 桃市議員憂心「不要變海市蜃樓」",
    "url": "https://news.ltn.com.tw/news/life/breakingnews/5372003",
    "image": "https://img.ltn.com.tw/Upload/news/600/2026/03/16/5372003_1_1.jpg",
    "published_at": "2026-03-16T08:04:26+00:00",
    "source": "LTN"
  },
  {
    "time": "15:55",
    "title": "竹科三期超高壓變電所大火 晶圓廠與光電廠生產恐受影響",
    "url": "https://ec.ltn.com.tw/article/breakingnews/5372016",
    "image": "https://img.ltn.com.tw/Upload/business/page/800/2026/03/16/phpaJtAz1.jpg",
    "published_at": "2026-03-16T08:04:26+00:00",
    "source": "LTN"
  },
  {
    "time": "15:55",
    "title": "中東戰火無礙美軍售 我102枚愛三MSE飛彈今年抵台",
    "url": "https://news.ltn.com.tw/news/politics/breakingnews/5372018",
    "image": "https://img.ltn.com.tw/Upload/news/600/2026/03/16/5372018_1_1.jpg",
    "published_at": "2026-03-16T08:04:26+00:00",
    "source": "LTN"
  },
  {
    "time": "15:52",
    "title": "台灣醫療紅到海外！英男「痛到受不了」來台治療疝氣 大讚台灣健保",
    "url": "https://ec.ltn.com.tw/article/breakingnews/5372020",
    "image": "https://img.ltn.com.tw/Upload/business/page/800/2026/03/16/phpWt2sbo.jpg",
    "published_at": "2026-03-16T08:04:26+00:00",
    "source": "LTN"
  }
]