[
  {
    "time": "16:27",
    "title": "中國人大將審「民族團結法」 台聯：挑釁台灣國家正常化",
    "url": "https://news.ltn.com.tw/news/politics/breakingnews/5360008",
    "image": "https://img.ltn.com.tw/Upload/news/600/2026/03/05/phplrWOTm.jpg",
    "published_at": "2026-03-05T08:33:03+00:00",
    "source": "LTN"
  },
  {
    "time": "16:27",
    "title": "你算哪根蔥？印度主持人電爆中國專家 為台灣發聲畫面瘋傳",
    "url": "https://news.ltn.com.tw/news/world/breakingnews/5359600",
    "image": "https://img.ltn.com.tw/Upload/news/600/2026/03/05/phpVtYgMK.jpg",
    "published_at": "2026-03-05T08:33:03+00:00",
    "source": "LTN"
  },
  {
    "time": "16:25",
    "title": "金屬工業研究發展中心63年成果展 羅達生：國際高階製造鏈的重要底氣",
    "url": "https://news.ltn.com.tw/news/life/breakingnews/5360065",
    "image": "https://img.ltn.com.tw/Upload/news/600/2026/03/05/5360065_2_1.jpg",
    "published_at": "2026-03-05T08:33:03+00:00",
    "source": "LTN"
  },
  {
    "time": "16:25",
    "title": "司法官律師二試採電腦化測驗 模擬作答網站3月下旬上線",
    "url": "https://news.ltn.com.tw/news/life/breakingnews/5360064",
    "image": "https://img.ltn.com.tw/Upload/news/600/2026/03/05/5360064_1_1.jpg",
    "published_at": "2026-03-05T08:33:03+00:00",
    "source": "LTN"
  },
  {
    "time": "16:25",
    "title": "Toyota 人氣 MPV 春季將推小改款！僅有 Hybrid 動力 今年在台生產",
    "url": "https://auto.ltn.com.tw/news/31089",
    "image": "https://img.ltn.com.tw/Upload/auto/page/2026/03/05/260305-31089-63-KM1Qt.jpeg",
    "published_at": "2026-03-05T08:33:03+00:00",
    "source": "LTN"
  },
  {
    "time": "16:24",
    "title": "Angelababy 遭軟封殺！生日零明星到場除了「她」",
    "url": "https://ent.ltn.com.tw/news/breakingnews/5360062",
    "image": "https://img.ltn.com.tw/Upload/ent/page/800/2026/03/05/phpGt3Lys.jpg",
    "published_at": "2026-03-05T08:33:03+00:00",
    "source": "LTN"
  },
  {
    "time": "16:23",
    "title": "第36個租稅協定 台灣與吐瓦魯正式簽署所得稅協定",
    "url": "https://ec.ltn.com.tw/article/breakingnews/5360068",
    "image": "https://img.ltn.com.tw/Upload/business/page/800/2026/03/05/5360068_1.jpg",
    "published_at": "2026-03-05T08:33:03+00:00",
    "source": "LTN"
  },
  {
    "time": "16:22",
    "title": "羅東土地公春遊擲筊最大獎1萬6800 馬年拚獎金一路發",
    "url": "https://news.ltn.com.tw/news/life/breakingnews/5359973",
    "image": "https://img.ltn.com.tw/Upload/news/600/2026/03/05/5359973_1_1.jpg",
    "published_at": "2026-03-05T08:33:03+00:00",
    "source": "LTN"
  }
]