[
  {
    "time": "06:10",
    "title": "中國軍艦曾通過 菲海軍擬於杜巴塔哈礁設監測站強化安全",
    "url": "https://news.ltn.com.tw/news/world/breakingnews/5334337",
    "image": "https://img.ltn.com.tw/Upload/news/600/2026/02/06/5334337_1_1.jpg",
    "published_at": "2026-02-05T22:20:59+00:00",
    "source": "LTN"
  },
  {
    "time": "06:03",
    "title": "川普與英相通話談狄耶戈加西亞島 警告租約若生變將動武捍衛",
    "url": "https://news.ltn.com.tw/news/world/breakingnews/5334339",
    "image": "https://img.ltn.com.tw/Upload/news/600/2026/02/06/5334339_1_1.jpg",
    "published_at": "2026-02-05T22:20:59+00:00",
    "source": "LTN"
  },
  {
    "time": "06:03",
    "title": "川普公開為高市背書催票 「她絕對不會讓日本人民失望！」",
    "url": "https://news.ltn.com.tw/news/world/breakingnews/5334343",
    "image": "https://img.ltn.com.tw/Upload/news/600/2026/02/06/5334343_1_1.jpg",
    "published_at": "2026-02-05T22:20:59+00:00",
    "source": "LTN"
  },
  {
    "time": "05:59",
    "title": "美股收盤》道瓊重挫近600點！台積電ADR反漲逾1.5％",
    "url": "https://ec.ltn.com.tw/article/breakingnews/5334352",
    "image": "https://img.ltn.com.tw/Upload/business/page/800/2026/02/06/php8Wbf5Q.jpg",
    "published_at": "2026-02-05T22:20:59+00:00",
    "source": "LTN"
  },
  {
    "time": "05:59",
    "title": "法國海軍採購空巴Aliaca垂直起降無人機 強化偵蒐戰力",
    "url": "https://news.ltn.com.tw/news/def/breakingnews/5334332",
    "image": "https://img.ltn.com.tw/Upload/def/page/800/2026/02/06/5334332_1_1.jpg",
    "published_at": "2026-02-05T22:20:59+00:00",
    "source": "LTN"
  },
  {
    "time": "05:58",
    "title": "晦氣、衰氣、病氣掃光光！12生肖做對居家大掃除「旺財旺運」一整年",
    "url": "https://ent.ltn.com.tw/news/breakingnews/5334316",
    "image": "https://img.ltn.com.tw/Upload/ent/page/800/2026/02/05/phpmPJXnQ.jpg",
    "published_at": "2026-02-05T22:20:59+00:00",
    "source": "LTN"
  },
  {
    "time": "05:54",
    "title": "美股續挫 道瓊收跌近600點",
    "url": "https://ec.ltn.com.tw/article/breakingnews/5334351",
    "image": "https://ec.ltn.com.tw/assets/images/1200_ec.png",
    "published_at": "2026-02-05T22:20:59+00:00",
    "source": "LTN"
  },
  {
    "time": "05:45",
    "title": "【時尚大道】年度腕錶限定祝福 駿馬逐時．腕間奔馳",
    "url": "https://istyle.ltn.com.tw/article/39079",
    "image": "https://img.ltn.com.tw/Upload/style/page/2026/02/04/o-260204-39079-0-Hy8Je.jpg",
    "published_at": "2026-02-05T22:20:59+00:00",
    "source": "LTN"
  }
]