[
  {
    "time": "22:14",
    "title": "中壢仁海宮點燈起跑！8旬嬤徹夜排隊搶頭香 首日湧3千人",
    "url": "https://news.ltn.com.tw/news/life/breakingnews/5315316",
    "image": "https://img.ltn.com.tw/Upload/news/600/2026/01/19/5315316_1_1.jpg",
    "published_at": "2026-01-19T14:21:15+00:00",
    "source": "LTN"
  },
  {
    "time": "22:13",
    "title": "EXO王者回歸！D.O.虧世勳當完兵像大叔 滿場跑只為找廁所",
    "url": "https://ent.ltn.com.tw/news/breakingnews/5315330",
    "image": "https://img.ltn.com.tw/Upload/ent/page/800/2026/01/19/phpSW1486.jpg",
    "published_at": "2026-01-19T14:21:15+00:00",
    "source": "LTN"
  },
  {
    "time": "22:13",
    "title": "健康網》年前搶修臉！醫美熱潮升溫 短修復微整最夯",
    "url": "https://health.ltn.com.tw/article/breakingnews/5311439",
    "image": "https://img.ltn.com.tw/Upload/health/page/800/2026/01/15/phpW5OreP.jpg",
    "published_at": "2026-01-19T14:21:15+00:00",
    "source": "LTN"
  },
  {
    "time": "22:06",
    "title": "千葉知事宣傳「慶賀之魚」金目鯛 日駐台代表盼藉美食深化台日情誼",
    "url": "https://news.ltn.com.tw/news/politics/breakingnews/5315313",
    "image": "https://img.ltn.com.tw/Upload/news/600/2026/01/19/5315313_3_1.jpg",
    "published_at": "2026-01-19T14:21:15+00:00",
    "source": "LTN"
  },
  {
    "time": "22:04",
    "title": "蘆洲逆子殘忍弒雙親 高大成揭可能犯案過程",
    "url": "https://news.ltn.com.tw/news/society/breakingnews/5315323",
    "image": "https://img.ltn.com.tw/Upload/news/600/2026/01/19/5315323_1_1.jpg",
    "published_at": "2026-01-19T14:21:15+00:00",
    "source": "LTN"
  },
  {
    "time": "22:03",
    "title": "被雷曼兄弟害慘了 《FX戰士久留美》宣布改編電視動畫",
    "url": "https://ent.ltn.com.tw/news/breakingnews/5315315",
    "image": "https://img.ltn.com.tw/Upload/ent/page/800/2026/01/19/php6HEpua.jpg",
    "published_at": "2026-01-19T14:21:15+00:00",
    "source": "LTN"
  },
  {
    "time": "22:01",
    "title": "八點檔男星「感情坎坷」 老婆失蹤又放不下前女友...私下面遭公開",
    "url": "https://ent.ltn.com.tw/news/breakingnews/5315324",
    "image": "https://img.ltn.com.tw/Upload/ent/page/800/2026/01/19/5315324_1.jpg",
    "published_at": "2026-01-19T14:21:15+00:00",
    "source": "LTN"
  },
  {
    "time": "22:00",
    "title": "威力彩頭獎連24摃 下期獎金上看6.3億",
    "url": "https://ec.ltn.com.tw/article/breakingnews/5315314",
    "image": "https://img.ltn.com.tw/Upload/business/page/800/2026/01/19/5315314_1.jpg",
    "published_at": "2026-01-19T14:21:15+00:00",
    "source": "LTN"
  }
]