[
  {
    "time": "22:52",
    "title": "基隆私幼虐童案延燒 謝國樑：第二階段調查後考慮廢照",
    "url": "https://news.ltn.com.tw/news/society/breakingnews/5494048",
    "image": "https://img.ltn.com.tw/Upload/news/600/2026/07/04/5494048_1_1.jpg",
    "published_at": "2026-07-04T15:00:03+00:00",
    "source": "LTN"
  },
  {
    "time": "22:48",
    "title": "屏東夏日狂歡祭來了！首晚巧虎音樂劇演出 千名親子同樂",
    "url": "https://news.ltn.com.tw/news/life/breakingnews/5494061",
    "image": "https://img.ltn.com.tw/Upload/news/600/2026/07/04/5494061_5_1.jpg",
    "published_at": "2026-07-04T15:00:03+00:00",
    "source": "LTN"
  },
  {
    "time": "22:45",
    "title": "少女時代Yuri爆離開SM！合作25年合約8月到期「傳轉投演員公司」",
    "url": "https://ent.ltn.com.tw/news/breakingnews/5494079",
    "image": "https://img.ltn.com.tw/Upload/ent/page/800/2026/07/04/5494079_1.jpg",
    "published_at": "2026-07-04T15:00:03+00:00",
    "source": "LTN"
  },
  {
    "time": "22:43",
    "title": "楊梅秀才路178巷拓寬延伸 9月辦理土地分割",
    "url": "https://news.ltn.com.tw/news/life/breakingnews/5493974",
    "image": "https://img.ltn.com.tw/Upload/news/600/2026/07/04/5493974_1_1.jpg",
    "published_at": "2026-07-04T15:00:03+00:00",
    "source": "LTN"
  },
  {
    "time": "22:39",
    "title": "（直擊）RAIN無預警走下台！粉絲失控離開座位：歐巴啊～～",
    "url": "https://ent.ltn.com.tw/news/breakingnews/5494077",
    "image": "https://img.ltn.com.tw/Upload/ent/page/800/2026/07/04/5494077_2.jpg",
    "published_at": "2026-07-04T15:00:03+00:00",
    "source": "LTN"
  },
  {
    "time": "22:35",
    "title": "致癌油元凶指向「巴西黃豆」 食藥署擬訂12.5％含水率標準",
    "url": "https://news.ltn.com.tw/news/life/breakingnews/5494074",
    "image": "https://img.ltn.com.tw/Upload/news/600/2026/07/04/phpOtCP7G.jpg",
    "published_at": "2026-07-04T15:00:03+00:00",
    "source": "LTN"
  },
  {
    "time": "22:33",
    "title": "美國獨立250年「驚訝嗎？」 威廉王子上節目接招還爆料",
    "url": "https://news.ltn.com.tw/news/world/breakingnews/5494078",
    "image": "https://img.ltn.com.tw/Upload/news/600/2026/07/04/5494078_1_1.jpg",
    "published_at": "2026-07-04T15:00:03+00:00",
    "source": "LTN"
  },
  {
    "time": "22:31",
    "title": "中職》味全龍開箱21歲左投！ 留下完美的第一印象",
    "url": "https://sports.ltn.com.tw/news/breakingnews/5494072",
    "image": "https://img.ltn.com.tw/Upload/sports/page/800S/2026/07/04/phpAqlFNT.jpg",
    "published_at": "2026-07-04T15:00:03+00:00",
    "source": "LTN"
  }
]