[
  {
    "time": "03:54",
    "title": "3週內2死 美明尼阿波利斯移民官射殺民眾再掀爭議",
    "url": "https://news.ltn.com.tw/news/world/breakingnews/5321216",
    "image": "https://news.ltn.com.tw/assets/images/all/250_ltn.png",
    "published_at": "2026-01-24T20:15:45+00:00",
    "source": "LTN"
  },
  {
    "time": "03:00",
    "title": "《TAIPEI TIMES》 China purge could disrupt chain of command: source",
    "url": "https://news.ltn.com.tw/news/focus/breakingnews/5321170",
    "image": "https://img.ltn.com.tw/Upload/news/600/2026/01/24/phpe0U4dV.jpg",
    "published_at": "2026-01-24T20:15:45+00:00",
    "source": "LTN"
  },
  {
    "time": "03:00",
    "title": "《TAIPEI TIMES》 Passenger accident turns into ad hoc airport art",
    "url": "https://news.ltn.com.tw/news/focus/breakingnews/5321174",
    "image": "https://img.ltn.com.tw/Upload/news/600/2026/01/24/phpZvRKdl.jpg",
    "published_at": "2026-01-24T20:15:45+00:00",
    "source": "LTN"
  },
  {
    "time": "03:00",
    "title": "《TAIPEI TIMES》 MOE to reform study program to attract top talent",
    "url": "https://news.ltn.com.tw/news/focus/breakingnews/5321179",
    "image": "https://img.ltn.com.tw/Upload/news/600/2026/01/24/phpGFhTet.jpg",
    "published_at": "2026-01-24T20:15:45+00:00",
    "source": "LTN"
  },
  {
    "time": "03:00",
    "title": "《TAIPEI TIMES》 Expert warns of risks of adopting pets as therapy",
    "url": "https://news.ltn.com.tw/news/focus/breakingnews/5321175",
    "image": "https://img.ltn.com.tw/Upload/news/600/2026/01/24/phpmjdMvA.jpg",
    "published_at": "2026-01-24T20:15:45+00:00",
    "source": "LTN"
  },
  {
    "time": "03:00",
    "title": "《TAIPEI TIMES》 Joseph Wu vows defense investment",
    "url": "https://news.ltn.com.tw/news/focus/breakingnews/5321176",
    "image": "https://img.ltn.com.tw/Upload/news/600/2026/01/24/php3EjF18.jpg",
    "published_at": "2026-01-24T20:15:45+00:00",
    "source": "LTN"
  },
  {
    "time": "03:00",
    "title": "《TAIPEI TIMES》 Pentagon document prioritizes homeland security",
    "url": "https://news.ltn.com.tw/news/focus/breakingnews/5321177",
    "image": "https://img.ltn.com.tw/Upload/news/600/2026/01/24/phpL2fAXb.jpg",
    "published_at": "2026-01-24T20:15:45+00:00",
    "source": "LTN"
  },
  {
    "time": "03:00",
    "title": "《TAIPEI TIMES》 Childbirth accidents drop to 7-year low",
    "url": "https://news.ltn.com.tw/news/focus/breakingnews/5321171",
    "image": "https://img.ltn.com.tw/Upload/news/600/2026/01/24/php3ACnqH.jpg",
    "published_at": "2026-01-24T20:15:45+00:00",
    "source": "LTN"
  }
]