[
  {
    "time": "19:19",
    "title": "失業男幫友人跑腿交易毒品沒收錢 法官認販毒判刑2年10月",
    "url": "https://news.ltn.com.tw/news/society/breakingnews/5366943",
    "image": "https://img.ltn.com.tw/Upload/news/600/2026/03/11/5366943_1_1.jpg",
    "published_at": "2026-03-11T11:28:11+00:00",
    "source": "LTN"
  },
  {
    "time": "19:18",
    "title": "暖冬少雨 台南鹽水硬質玉米產量銳減",
    "url": "https://news.ltn.com.tw/news/life/breakingnews/5367029",
    "image": "https://img.ltn.com.tw/Upload/news/600/2026/03/11/5367029_2_1.jpg",
    "published_at": "2026-03-11T11:28:11+00:00",
    "source": "LTN"
  },
  {
    "time": "19:17",
    "title": "表態「沒有要再選」被問下一步 王惠美笑回這句話",
    "url": "https://news.ltn.com.tw/news/politics/breakingnews/5367056",
    "image": "https://img.ltn.com.tw/Upload/news/600/2026/03/11/5367056_1_1.jpg",
    "published_at": "2026-03-11T11:28:11+00:00",
    "source": "LTN"
  },
  {
    "time": "19:16",
    "title": "經典賽》日媒爆山本由伸再扛先發！日本「大聯盟武士接力」抗多、委",
    "url": "https://sports.ltn.com.tw/news/breakingnews/5367038",
    "image": "https://img.ltn.com.tw/Upload/sports/page/800S/2026/03/11/phpMkFjTU.jpg",
    "published_at": "2026-03-11T11:28:11+00:00",
    "source": "LTN"
  },
  {
    "time": "19:16",
    "title": "枋山鄉長外遇遭偷拍勒索 徵信業者勾結多名刑警洩密收賄 判決出爐",
    "url": "https://news.ltn.com.tw/news/society/breakingnews/5367018",
    "image": "https://img.ltn.com.tw/Upload/news/600/2026/03/11/5367018_1_1.jpg",
    "published_at": "2026-03-11T11:28:11+00:00",
    "source": "LTN"
  },
  {
    "time": "19:14",
    "title": "真好康！南投縣府員工享視障按摩紓壓服務",
    "url": "https://news.ltn.com.tw/news/life/breakingnews/5366986",
    "image": "https://img.ltn.com.tw/Upload/news/600/2026/03/11/5366986_1_1.jpg",
    "published_at": "2026-03-11T11:28:11+00:00",
    "source": "LTN"
  },
  {
    "time": "19:13",
    "title": "Costco多款熱門商品「悄悄」降價了 促銷標語不會讓你看到",
    "url": "https://ec.ltn.com.tw/article/breakingnews/5367067",
    "image": "https://img.ltn.com.tw/Upload/business/page/800/2026/03/11/phpuRlPrc.jpg",
    "published_at": "2026-03-11T11:28:11+00:00",
    "source": "LTN"
  },
  {
    "time": "19:11",
    "title": "單車阿北不爽被叭怒擋客運 還抄車鎖砸頭打前議員金介壽",
    "url": "https://news.ltn.com.tw/news/society/breakingnews/5366961",
    "image": "https://img.ltn.com.tw/Upload/news/600/2026/03/11/5366961_1_1.jpg",
    "published_at": "2026-03-11T11:28:11+00:00",
    "source": "LTN"
  }
]